flyway/__init__.py
flyway/database.py
flyway/db_type.py
flyway/migrator.py
flyway/py.typed
flyway/schema.py
flyway-0.2.0.dist-info/licenses/LICENSE
flyway-0.2.0.dist-info/METADATA
flyway-0.2.0.dist-info/WHEEL
flyway-0.2.0.dist-info/top_level.txt
flyway-0.2.0.dist-info/RECORD
