Metadata-Version: 2.4
Name: flyway
Version: 0.2.0
Project-URL: Homepage, https://github.com/hezhangjian/flyway-python
Project-URL: Repository, https://github.com/hezhangjian/flyway-python
Project-URL: Documentation, https://github.com/hezhangjian/flyway-python#readme
Requires-Python: >=3.11
License-File: LICENSE
Provides-Extra: dev
Requires-Dist: mypy; extra == "dev"
Requires-Dist: ruff; extra == "dev"
Requires-Dist: types-PyMySQL; extra == "dev"
Provides-Extra: test
Requires-Dist: mysql-connector-python; extra == "test"
Requires-Dist: pymysql; extra == "test"
Requires-Dist: pytest; extra == "test"
Requires-Dist: testcontainers; extra == "test"
Dynamic: license-file
